{"isin": "IT0005614182", "lastUpdatedOn": "2025-01-31", "data": [{"date": "2025-01-31", "close": 99.613}, {"date": "2025-01-30", "close": 99.6}, {"date": "2025-01-29", "close": 99.576}, {"date": "2025-01-28", "close": 99.569}, {"date": "2025-01-27", "close": 99.563}, {"date": "2025-01-24", "close": 99.55}, {"date": "2025-01-23", "close": 99.542}, {"date": "2025-01-22", "close": 99.518}, {"date": "2025-01-21", "close": 99.51}, {"date": "2025-01-20", "close": 99.503}, {"date": "2025-01-17", "close": 99.497}, {"date": "2025-01-16", "close": 99.499}, {"date": "2025-01-15", "close": 99.471}, {"date": "2025-01-14", "close": 99.466}, {"date": "2025-01-13", "close": 99.46}, {"date": "2025-01-10", "close": 99.456}, {"date": "2025-01-09", "close": 99.449}, {"date": "2025-01-08", "close": 99.429}, {"date": "2025-01-07", "close": 99.432}, {"date": "2025-01-06", "close": 99.421}, {"date": "2025-01-03", "close": 99.416}, {"date": "2025-01-02", "close": 99.418}, {"date": "2024-12-31", "close": 99.369}, {"date": "2024-12-30", "close": 99.369}, {"date": "2024-12-27", "close": 99.354}, {"date": "2024-12-24", "close": 99.315}, {"date": "2024-12-23", "close": 99.315}, {"date": "2024-12-20", "close": 99.299}, {"date": "2024-12-19", "close": 99.279}, {"date": "2024-12-18", "close": 99.263}, {"date": "2024-12-17", "close": 99.249}, {"date": "2024-12-16", "close": 99.35}, {"date": "2024-12-13", "close": 99.24}, {"date": "2024-12-12", "close": 99.233}, {"date": "2024-12-11", "close": 99.195}, {"date": "2024-12-10", "close": 99.317}, {"date": "2024-12-09", "close": 99.188}, {"date": "2024-12-06", "close": 99.171}, {"date": "2024-12-05", "close": 99.172}, {"date": "2024-12-04", "close": 99.139}, {"date": "2024-12-03", "close": 99.128}, {"date": "2024-12-02", "close": 99.119}, {"date": "2024-11-29", "close": 99.108}, {"date": "2024-11-28", "close": 99.094}, {"date": "2024-11-27", "close": 99.067}, {"date": "2024-11-26", "close": 99.074}, {"date": "2024-11-25", "close": 99.065}, {"date": "2024-11-22", "close": 99.064}, {"date": "2024-11-21", "close": 99.042}, {"date": "2024-11-20", "close": 98.994}, {"date": "2024-11-19", "close": 98.975}, {"date": "2024-11-18", "close": 98.977}, {"date": "2024-11-15", "close": 98.966}, {"date": "2024-11-14", "close": 98.959}, {"date": "2024-11-13", "close": 98.91}, {"date": "2024-11-12", "close": 98.905}, {"date": "2024-11-11", "close": 98.885}, {"date": "2024-11-08", "close": 98.876}, {"date": "2024-11-07", "close": 98.862}, {"date": "2024-11-06", "close": 98.995}, {"date": "2024-11-05", "close": 98.816}, {"date": "2024-11-04", "close": 98.796}, {"date": "2024-11-01", "close": 98.799}, {"date": "2024-10-31", "close": 98.785}, {"date": "2024-10-30", "close": 98.766}, {"date": "2024-10-29", "close": 98.767}, {"date": "2024-10-28", "close": 98.755}, {"date": "2024-10-25", "close": 98.74}, {"date": "2024-10-24", "close": 98.751}, {"date": "2024-10-23", "close": 98.715}, {"date": "2024-10-22", "close": 98.7}, {"date": "2024-10-21", "close": 98.702}, {"date": "2024-10-18", "close": 98.702}, {"date": "2024-10-17", "close": 98.672}, {"date": "2024-10-16", "close": 98.796}, {"date": "2024-10-15", "close": 98.79}, {"date": "2024-10-14", "close": 98.599}, {"date": "2024-10-11", "close": 98.576}, {"date": "2024-10-10", "close": 98.589}, {"date": "2024-10-09", "close": 98.564}, {"date": "2024-10-08", "close": 98.585}, {"date": "2024-10-07", "close": 98.585}, {"date": "2024-10-04", "close": 98.544}, {"date": "2024-10-03", "close": 98.585}, {"date": "2024-10-02", "close": 98.585}, {"date": "2024-10-01", "close": 98.717}, {"date": "2024-09-30", "close": 98.481}, {"date": "2024-09-27", "close": 98.469}]}